{
 "province": "青海", 
 "city": "西宁 ", 
 "advantage": [
  "普通装修"
 ], 
 "district": "西门", 
 "title": "天桥相府，办公居家好房", 
 "url_now": "http://xn.58.com/zufang/34393662875084x.shtml", 
 "region": "西北", 
 "area": "2室1厅1卫                                  49                                平  简单装修 ", 
 "contacts": "杨宇斌(经纪人)", 
 "community": "城中", 
 "detail": "未提供描述", 
 "facility": "热水器.", 
 "phone": "18581031176", 
 "rental_type": "整租", 
 "rent": "2400", 
 "address": "\n                                天桥相府                            ", 
 "pics": [
  "http://pic5.58cdn.com.cn/anjuke_58/b07f1aa2d957112359edb2c6de7f7bf8?w=696&h=522&crop=1", 
  "http://pic5.58cdn.com.cn/anjuke_58/e59a651a030435cc72f44dc521f1b237?w=696&h=522&crop=1", 
  "http://pic7.58cdn.com.cn/anjuke_58/0e676c7da31c7a92b890e5533668d717?w=696&h=522&crop=1", 
  "http://pic7.58cdn.com.cn/anjuke_58/cb89896e9a7ad515dd641c26909e2510?w=696&h=522&crop=1", 
  "http://pic7.58cdn.com.cn/anjuke_58/cfae067a1bd57f5320880c646b39ec74?w=696&h=522&crop=1"
 ], 
 "heading": "北  低层/共36层", 
 "lease": "年付"
}