{
 "province": "内蒙古", 
 "city": "巴彦淖尔市 ", 
 "advantage": [
  "配套齐全", 
  "精装修"
 ], 
 "district": "杭锦后旗", 
 "title": "奋斗中学对面 玫瑰园四楼精装修带家具 随时看房、随时入住", 
 "url_now": "http://bycem.58.com/zufang/34461214671915x.shtml", 
 "region": "华北", 
 "area": "2室2厅2卫  95平  精装修", 
 "contacts": "谢彦博(经纪人)", 
 "community": "杭锦后旗", 
 "detail": "未提供描述", 
 "facility": "床.衣柜.沙发.热水器.宽带.暖气.阳台.", 
 "phone": "15389785070", 
 "rental_type": "整租", 
 "rent": "1350", 
 "address": "\n                                暂无信息                            ", 
 "pics": [
  "http://pic4.58cdn.com.cn/anjuke_58/e6611ca13131cd1a8f03782787bd56bd?w=696&h=522&crop=1", 
  "http://pic2.58cdn.com.cn/anjuke_58/3d44d3f56286922a1657e68b8dd6c50e?w=696&h=522&crop=1", 
  "http://pic2.58cdn.com.cn/anjuke_58/ccc845b1618a318f958bcf12c6c07232?w=696&h=522&crop=1", 
  "http://pic2.58cdn.com.cn/anjuke_58/63399d470bc6b8f6c0c3c7caac08e902?w=696&h=522&crop=1", 
  "http://pic2.58cdn.com.cn/anjuke_58/01d9d3eb4c648816a40455efedbbacb9?w=696&h=522&crop=1", 
  "http://pic1.58cdn.com.cn/anjuke_58/660f9ca1972d7a94d0a59af6e9df3eb0?w=696&h=522&crop=1", 
  "http://pic5.58cdn.com.cn/anjuke_58/19c0a4b307f8313999403169e2470e8d?w=696&h=522&crop=1", 
  "http://pic7.58cdn.com.cn/anjuke_58/696f40960b9132bda92f2988200deef9?w=696&h=522&crop=1"
 ], 
 "heading": "南北  共5层", 
 "lease": "年付"
}