{
 "province": "山东", 
 "city": "潍坊 ", 
 "advantage": [
  "普通装修"
 ], 
 "district": "高新区", 
 "title": "《明珠无虚假》市附近精装全套6居室诚意出租", 
 "url_now": "http://wf.58.com/zufang/34439830620869x.shtml", 
 "region": "华中", 
 "area": "6室2厅2卫                                  171                                平  简单装修 ", 
 "contacts": "李少龙(经纪人)", 
 "community": "泛海城市花园", 
 "detail": "明珠不动产郑重：", 
 "facility": "业主未提供此方面的信息", 
 "phone": "18863636750", 
 "rental_type": "整租", 
 "rent": "2380", 
 "address": "未提供", 
 "pics": [
  "http://pic8.58cdn.com.cn/anjuke_58/915519eacb25419eeb9a55149605ab3f?w=696&h=522&crop=1", 
  "http://pic7.58cdn.com.cn/anjuke_58/01e9ea7c6fe30d8b7480be5dc2b86b9c?w=696&h=522&crop=1", 
  "http://pic7.58cdn.com.cn/anjuke_58/02c24060cb2a0d6efdff4994dd53e6a0?w=696&h=522&crop=1", 
  "http://pic2.58cdn.com.cn/anjuke_58/d918b0e8f0783aab7470cf172483a703?w=696&h=522&crop=1", 
  "http://pic2.58cdn.com.cn/anjuke_58/c0112eebd3d78c05f80819df223e26de?w=696&h=522&crop=1"
 ], 
 "heading": "南北  共5层", 
 "lease": "押一付三"
}