{
 "province": "云南", 
 "city": "楚雄 ", 
 "advantage": "配套齐全", 
 "district": "楚雄", 
 "title": "州政务中心华府世家旁四季银座两居室精装修拎包入住", 
 "url_now": "http://cx.58.com/zufang/33962642790220x.shtml", 
 "region": "西南", 
 "area": "2室2厅2卫                                  100                                平  精装修 ", 
 "contacts": "杨丽娟(经纪人)", 
 "community": "楚雄", 
 "detail": "房子位于四季银座两室两厅一厨一卫，带全套家具，租金1400元，小区环境好，停车方便，房子干净整洁安静舒适采光好，周边设施全，有意者请与我联系看房", 
 "facility": "床.衣柜.沙发.电视.热水器.宽带.阳台.", 
 "phone": "13529519947", 
 "rental_type": "整租", 
 "rent": "1400", 
 "address": "\n                                四季银座                            ", 
 "pics": [
  "http://pic8.58cdn.com.cn/anjuke_58/e6cd0387bf1cad43a2f8a3d5b21c3df7?w=696&h=522&crop=1", 
  "http://pic6.58cdn.com.cn/anjuke_58/f4d9077ea3f7eb864aa40074681e4d4c?w=696&h=522&crop=1"
 ], 
 "heading": "南北  中层/共23层", 
 "lease": "面议"
}