{
 "province": "安徽", 
 "city": "滁州 ", 
 "advantage": [
  "普通装修"
 ], 
 "district": "琅琊", 
 "title": "泰鑫中环国际 办公房（45~145平米均有）有钥匙 随时看房", 
 "url_now": "http://chuzhou.58.com/zufang/34379528923083x.shtml", 
 "region": "华中", 
 "area": "2室2厅1卫  100平  简单装修", 
 "contacts": "孙金梅(经纪人)", 
 "community": "泰鑫中环国际广场", 
 "detail": "此房处于市中心核心地段，白云商厦楼上，出行交通十分方便。（步行*到1912广场  苏宁购物广场 南湖公园 ） 此房交适合办公或做工作室，图片真实 ，看房方便，除了此套还有多套房源供您选择。欢迎来电  13956319382  **同号  欢迎来看实地房。", 
 "facility": "空调.热水器.阳台.", 
 "phone": "13956319382", 
 "rental_type": "整租", 
 "rent": "1500", 
 "address": "\n                                南谯北路688号                            ", 
 "pics": [
  "http://pic6.58cdn.com.cn/anjuke_58/ca23acf1265943f958b7a2e3002d7b7f?w=696&h=522&crop=1", 
  "http://pic4.58cdn.com.cn/anjuke_58/9e7ea00c598559a66c508a44d3325bf4?w=696&h=522&crop=1", 
  "http://pic4.58cdn.com.cn/anjuke_58/1b3e7bd1fed59c105bb0c3ae8ab6adea?w=696&h=522&crop=1", 
  "http://pic7.58cdn.com.cn/anjuke_58/de646bd32113aeb9a3c76292a5a1c1f6?w=696&h=522&crop=1", 
  "http://pic7.58cdn.com.cn/anjuke_58/7eef972e1639b8837b4fc128f25c2a73?w=696&h=522&crop=1", 
  "http://pic7.58cdn.com.cn/anjuke_58/6c24efbd3e070695d3c70c58969edc07?w=696&h=522&crop=1"
 ], 
 "heading": "南  中层/共28层", 
 "lease": "押一付三"
}