{
 "province": "安徽", 
 "city": "阜阳 ", 
 "advantage": [
  "配套齐全", 
  "精装修"
 ], 
 "district": "颍州", 
 "title": "城南万达华府 全新装修 家电齐全 采光好 黄0金楼层 拎包入", 
 "url_now": "http://fy.58.com/zufang/34413245676092x.shtml", 
 "region": "华中", 
 "area": "3室2厅1卫  115平  精装修", 
 "contacts": "付运想(经纪人)", 
 "community": "颍州", 
 "detail": [
  "房屋情况介绍：", 
  " ", 
  "：房子精装修，家电齐全，", 
  " 2", 
  "：现有", 
  " 3", 
  " 4：", 
  "银行:暂无资料", 
  " ", 
  " 5", 
  "可能此房信息不够详细，", 
  " ", 
  "如果此房您不满意，", 
  " ", 
  "请与我联系，我会根据", 
  " ", 
  "如果您对此房源不满意，您可以点击我的头像会我的店铺，里面有更多的*供您选择。"
 ], 
 "facility": "床.冰箱.洗衣机.空调.热水器.暖气.阳台.", 
 "phone": "17355836520", 
 "rental_type": "整租", 
 "rent": "2300", 
 "address": "未提供", 
 "pics": [
  "http://pic6.58cdn.com.cn/anjuke_58/6de72206960450981396c38e3e3c63bc?w=696&h=522&crop=1", 
  "http://pic8.58cdn.com.cn/anjuke_58/a57e3ae2787e2569beefae5687df8055?w=696&h=522&crop=1", 
  "http://pic2.58cdn.com.cn/anjuke_58/75a4ec683fdfe36d7fcd6b1f4f5d06d5?w=696&h=522&crop=1", 
  "http://pic2.58cdn.com.cn/anjuke_58/49d7d17bb86f4985ea7bfc23e519cfc7?w=696&h=522&crop=1", 
  "http://pic1.58cdn.com.cn/anjuke_58/e0da2016a9b9f0052e1949ad61c580e1?w=696&h=522&crop=1", 
  "http://pic1.58cdn.com.cn/anjuke_58/b6e6f670e3c83ae0b9b09dea546d2a78?w=696&h=522&crop=1"
 ], 
 "heading": "南北  中层/共29层", 
 "lease": "面议"
}