{
 "province": "黑龙江", 
 "city": "绥化 ", 
 "advantage": [
  "普通装修", 
  "随时看房"
 ], 
 "district": "北林", 
 "title": "八副食对面林业商场楼上 2室1厅1卫(个人)", 
 "url_now": "http://suihua.58.com/zufang/34114509872683x.shtml", 
 "region": "东北", 
 "area": "2室1厅1卫  60平  简单装修", 
 "contacts": "沈女士(个人)", 
 "community": "北林", 
 "detail": "未提供描述", 
 "facility": "床.", 
 "phone": "站点未提供此内容", 
 "rental_type": "整租", 
 "rent": "6500", 
 "address": "\n                                黑龙江省绥化市北林区                            ", 
 "pics": [], 
 "heading": "南北  共5层", 
 "lease": "押一付三"
}