{
 "province": "新疆", 
 "city": "石河子 ", 
 "advantage": "配套齐全", 
 "district": "东城", 
 "title": "景盛园 3室2厅2卫", 
 "url_now": "http://shz.58.com/zufang/34403201825851x.shtml", 
 "region": "西北", 
 "area": "3室2厅2卫                                  132                                平  简单装修 ", 
 "contacts": "马勇 (经纪人)", 
 "community": "景盛园", 
 "detail": "\n                                                    ", 
 "facility": "床.衣柜.沙发.电视.冰箱.洗衣机.热水器.暖气.阳台.", 
 "phone": "13677546715", 
 "rental_type": "整租", 
 "rent": "1600", 
 "address": "\n                                景盛园                            ", 
 "pics": [
  "http://pic6.58cdn.com.cn/p1/big/n_v25f8605c8ed0949119a1d42bec673aa95.jpg?w=696&h=522&crop=1", 
  "http://pic3.58cdn.com.cn/p1/big/n_v2de24cda9e2ab4b808591aee8c8ac6b1f.jpg?w=696&h=522&crop=1", 
  "http://pic6.58cdn.com.cn/p1/big/n_v2c34c8294945543c6bb054059d23d450a.jpg?w=696&h=522&crop=1", 
  "http://pic7.58cdn.com.cn/p1/big/n_v293e7471e5e5c4c49b56ac13f3c8e1080.jpg?w=696&h=522&crop=1", 
  "http://pic6.58cdn.com.cn/p1/big/n_v2ecb2cfa803b74545a6446478b2b9cc2b.jpg?w=696&h=522&crop=1", 
  "http://pic8.58cdn.com.cn/p1/big/n_v220c0188c67144f2e9c16cbacbf681af3.jpg?w=696&h=522&crop=1", 
  "http://pic5.58cdn.com.cn/p1/big/n_v2073323b076034d4c8fcfb740439da0e9.jpg?w=696&h=522&crop=1", 
  "http://pic7.58cdn.com.cn/p1/big/n_v294c3a77a627f4ec1a772f43d1d6d4a7d.jpg?w=696&h=522&crop=1"
 ], 
 "heading": "南北  高层/共7层", 
 "lease": "年付"
}