{
 "province": "新疆", 
 "city": "喀什 ", 
 "advantage": [
  "配套齐全", 
  "精装修"
 ], 
 "district": "喀什", 
 "title": "环疆+鸿和苑小区+1楼+拎包入住", 
 "url_now": "http://ks.58.com/zufang/34446977611974x.shtml", 
 "region": "西北", 
 "area": "2室2厅1卫                                  90                                平  精装修 ", 
 "contacts": "胡娇娇(经纪人)", 
 "community": "喀什", 
 "detail": "未提供描述", 
 "facility": "床.衣柜.沙发.电视.冰箱.洗衣机.空调.热水器.宽带.暖气.阳台.", 
 "phone": "15599857755", 
 "rental_type": "整租", 
 "rent": "1333", 
 "address": "\n                                鸿和苑                            ", 
 "pics": [
  "http://pic7.58cdn.com.cn/anjuke_58/32f2e8656c9cfe2b5a3cc6b8b3e44306?w=696&h=522&crop=1", 
  "http://pic6.58cdn.com.cn/anjuke_58/ca20fef87aa41e2292a14bac4b4137ce?w=696&h=522&crop=1", 
  "http://pic1.58cdn.com.cn/anjuke_58/dde060645a2607d06561a45bfaa947b2?w=696&h=522&crop=1", 
  "http://pic8.58cdn.com.cn/anjuke_58/d7d9df4650b6fc97ecb2b2ae8c333e21?w=696&h=522&crop=1", 
  "http://pic8.58cdn.com.cn/anjuke_58/0e74df42554922e3c14a04e8e7cbee1e?w=696&h=522&crop=1", 
  "http://pic8.58cdn.com.cn/anjuke_58/50b99ba23ffa9f6e9ab0574369aad442?w=696&h=522&crop=1", 
  "http://pic8.58cdn.com.cn/anjuke_58/b7637c79796630ec4ac1293c14eb94fe?w=696&h=522&crop=1"
 ], 
 "heading": "东  共5层", 
 "lease": "年付"
}