{
 "province": "湖南", 
 "city": "武汉 ", 
 "advantage": [
  "邻地铁", 
  "押一付一", 
  "朝南", 
  "精装修"
 ], 
 "district": "江汉", 
 "title": "(单间出租)江汉小江家院 卧室朝向朝南 有飘窗 有厨房可饭", 
 "url_now": "http://wh.58.com/hezu/34480481104188x.shtml", 
 "region": "中南", 
 "area": "3室1厅1卫                                  10                                平  精装修 ", 
 "contacts": "蛋壳公寓(经纪人)", 
 "community": "小江家院", 
 "detail": "前进小江家院 有所居有好居", 
 "facility": "业主未提供此方面的信息", 
 "phone": "13036104527", 
 "rental_type": "合租 - 主卧 - 男女不限", 
 "rent": "850", 
 "address": "\n                                统一街230号                            ", 
 "pics": [
  "http://pic3.58cdn.com.cn/anjuke_58/dfac44de33265b8adfce4e17f5974e90?w=696&h=522&crop=1", 
  "http://pic4.58cdn.com.cn/anjuke_58/725df12a5f8ba5432c90fc970ff0578a?w=696&h=522&crop=1", 
  "http://pic5.58cdn.com.cn/anjuke_58/3e5bac13afebc0fa875c142cf2e16648?w=696&h=522&crop=1", 
  "http://pic4.58cdn.com.cn/anjuke_58/6923b56932b349871fecac414fad8f95?w=696&h=522&crop=1", 
  "http://pic4.58cdn.com.cn/anjuke_58/f0337dba20772f71599156e6fd2df083?w=696&h=522&crop=1", 
  "http://pic4.58cdn.com.cn/anjuke_58/9a401d9ddaffb84b21ea9e46c5550fd1?w=696&h=522&crop=1", 
  "http://pic4.58cdn.com.cn/anjuke_58/7e39b6a5836fc7c3237dad71ba646b11?w=696&h=522&crop=1", 
  "http://pic4.58cdn.com.cn/anjuke_58/aea73a561dc422a326a1044ed42e6482?w=696&h=522&crop=1"
 ], 
 "heading": "南  低层/共11层", 
 "lease": "押一付一"
}