{
 "province": "江苏", 
 "city": "如皋 ", 
 "advantage": [
  "配套齐全", 
  "南北通透", 
  "有阳台", 
  "首次出租"
 ], 
 "district": "如皋市区", 
 "title": "丰泽怡园(桃源路208号) 3室2厅2卫(个人)", 
 "url_now": "http://rugao.58.com/zufang/34401872264493x.shtml", 
 "region": "华中", 
 "area": "3室2厅2卫  128平  ", 
 "contacts": "夏先生(个人)", 
 "community": "丰泽怡园(桃源路208...", 
 "detail": "\n                                                    ", 
 "facility": "床.衣柜.沙发.电视.冰箱.热水器.宽带.阳台.", 
 "phone": "站点未提供此内容", 
 "rental_type": "整租", 
 "rent": "2800", 
 "address": "\n                                桃源路208号                            ", 
 "pics": [
  "http://pic8.58cdn.com.cn/dwater/fang/big/n_v2b2975d21bc724d9abdb51e8ca73e74a4.jpg?wt=%40%E5%A4%8F%E5%85%88%E7%94%9F&ws=9ab47b25930bf704f09519e7157004bd&w=696&h=522&crop=1", 
  "http://pic1.58cdn.com.cn/dwater/fang/big/n_v2553f88eae9eb482b8e60ebfc03e02c8f.jpg?wt=%40%E5%A4%8F%E5%85%88%E7%94%9F&ws=0e263d15bdd86c611bb36ec6b9d00f1e&w=696&h=522&crop=1", 
  "http://pic8.58cdn.com.cn/dwater/fang/big/n_v2ff8aba5826784782b3284a326a8aa288.jpg?wt=%40%E5%A4%8F%E5%85%88%E7%94%9F&ws=4a4e9ebca55bbce972bb884d9a49b211&w=696&h=522&crop=1", 
  "http://pic1.58cdn.com.cn/dwater/fang/big/n_v29b1098062418446f9abd94fb7b97c59d.jpg?wt=%40%E5%A4%8F%E5%85%88%E7%94%9F&ws=23af5f89bff7e460ec357d61a3d85e4b&w=696&h=522&crop=1", 
  "http://pic3.58cdn.com.cn/dwater/fang/big/n_v2810affb3c0fd4e8caa42c39f1e2ee70f.jpg?wt=%40%E5%A4%8F%E5%85%88%E7%94%9F&ws=76902aefe3389c952d521ec17e9f509d&w=696&h=522&crop=1"
 ], 
 "heading": "南  中层/共31层", 
 "lease": "押一付三"
}