{
 "province": "山东", 
 "city": "滨州 ", 
 "advantage": [
  "配套齐全", 
  "普通装修"
 ], 
 "district": "沾化", 
 "title": "建筑公司，紧邻二小，带有热水器厨房全，沙发茶几，拎包入住", 
 "url_now": "http://bz.58.com/zufang/34250850766890x.shtml", 
 "region": "华中", 
 "area": "2室2厅1卫  80平  简单装修", 
 "contacts": "吴昊(经纪人)", 
 "community": "沾化", 
 "detail": "建筑公司，紧邻二小，带有热水器厨房全，沙发茶几，拎包入住", 
 "facility": "床.衣柜.沙发.空调.热水器.宽带.暖气.阳台.", 
 "phone": "13563082089", 
 "rental_type": "整租", 
 "rent": "1000", 
 "address": "\n                                富城路                            ", 
 "pics": [
  "http://pic2.58cdn.com.cn/anjuke_58/b2081aed92568303559204521a081319?w=696&h=522&crop=1", 
  "http://pic4.58cdn.com.cn/anjuke_58/baaf0340970e63b916f8cf488983442a?w=696&h=522&crop=1", 
  "http://pic4.58cdn.com.cn/anjuke_58/86047df8d0e38f5f772275bdc62cf336?w=696&h=522&crop=1", 
  "http://pic3.58cdn.com.cn/anjuke_58/faec6bb54de393eb45d2249d76821691?w=696&h=522&crop=1", 
  "http://pic4.58cdn.com.cn/anjuke_58/881ec210299cce0c0f67d436a70c2121?w=696&h=522&crop=1", 
  "http://pic6.58cdn.com.cn/anjuke_58/dd6e50c4bc756b8f5630ec03dd0c0775?w=696&h=522&crop=1"
 ], 
 "heading": "南北  共5层", 
 "lease": "年付"
}