{
 "province": "海南", 
 "city": "三亚 ", 
 "advantage": [
  "精装修"
 ], 
 "district": "吉阳区", 
 "title": "海螺路 同心家园 精装大3房 家电齐全 拎包入住", 
 "url_now": "http://sanya.58.com/zufang/34479971627854x.shtml", 
 "region": "华南", 
 "area": "3室2厅2卫  130平  精装修", 
 "contacts": "韦晶馨(经纪人)", 
 "community": "东岸假日", 
 "detail": "未提供描述", 
 "facility": "业主未提供此方面的信息", 
 "phone": "15008074304", 
 "rental_type": "整租", 
 "rent": "4100", 
 "address": "\n                                迎宾路404号                            ", 
 "pics": [
  "http://pic3.58cdn.com.cn/anjuke_58/e272df2717fa866d0f665da1634ac142?w=696&h=522&crop=1", 
  "http://pic2.58cdn.com.cn/anjuke_58/e7fd3d6c1374101a7b73abb422cd431a?w=696&h=522&crop=1", 
  "http://pic2.58cdn.com.cn/anjuke_58/df2476546a5230657740a691259c705a?w=696&h=522&crop=1", 
  "http://pic1.58cdn.com.cn/anjuke_58/20cb79791112d6a264d87930e73035f9?w=696&h=522&crop=1", 
  "http://pic4.58cdn.com.cn/anjuke_58/24a0ab192214f531b4a7833d1600b20e?w=696&h=522&crop=1", 
  "http://pic3.58cdn.com.cn/anjuke_58/9d98dd6dd821ac49469a5f4c2e11b1d0?w=696&h=522&crop=1", 
  "http://pic4.58cdn.com.cn/anjuke_58/60e29c5ebdb61f75388f9eeb625b35d0?w=696&h=522&crop=1"
 ], 
 "heading": "东南  高层/共25层", 
 "lease": "押一付三"
}