{
 "province": "吉林", 
 "city": "延边 ", 
 "advantage": [
  "押一付一", 
  "配套齐全", 
  "精装修"
 ], 
 "district": "中心区", 
 "title": "房租月交 市中心 新罗世界 电梯楼 精装 白山大厦南侧河景", 
 "url_now": "http://yanbian.58.com/zufang/34435742273865x.shtml", 
 "region": "东北", 
 "area": "1室0厅1卫  50平  精装修", 
 "contacts": "安丰田(经纪人)", 
 "community": "延吉", 
 "detail": "床 衣柜 沙发 电视 冰箱 洗衣机 热水器 宽带 暖气 可做饭 独立卫生间", 
 "facility": "床.衣柜.沙发.电视.冰箱.洗衣机.热水器.宽带.暖气.阳台.", 
 "phone": "15694334442", 
 "rental_type": "整租", 
 "rent": "1600", 
 "address": "未提供", 
 "pics": [
  "http://pic6.58cdn.com.cn/anjuke_58/2f6276138229ad022138fbe3d867a05b?w=696&h=522&crop=1", 
  "http://pic5.58cdn.com.cn/anjuke_58/27989486f703bf3f51d2ccff10c9bee0?w=696&h=522&crop=1", 
  "http://pic7.58cdn.com.cn/anjuke_58/4dc87ac492c0286fec432c1cd03db568?w=696&h=522&crop=1", 
  "http://pic7.58cdn.com.cn/anjuke_58/957354b676d3eb6030da25c1f1ef4a4a?w=696&h=522&crop=1", 
  "http://pic7.58cdn.com.cn/anjuke_58/74041788fb53830d13dc0a1a884d1c0a?w=696&h=522&crop=1", 
  "http://pic7.58cdn.com.cn/anjuke_58/b0b12f79ca6614f182ef09d9cbbe3095?w=696&h=522&crop=1", 
  "http://pic6.58cdn.com.cn/anjuke_58/223dd3aa21421c27ae834aaabb738487?w=696&h=522&crop=1", 
  "http://pic7.58cdn.com.cn/anjuke_58/7cf19dd430b31de5e3de52bb3569d75a?w=696&h=522&crop=1"
 ], 
 "heading": "南  高层/共16层", 
 "lease": "押一付一"
}