{
 "province": "海南", 
 "city": "琼海 ", 
 "advantage": "独卫", 
 "district": "嘉积镇", 
 "title": "(单间出租)家具家电齐全 大三房未入住 有三台空调", 
 "url_now": "http://qh.58.com/hezu/34106918328489x.shtml", 
 "region": "华南", 
 "area": "3室2厅2卫                                  98                                平  精装修 ", 
 "contacts": "陈桂铃(经纪人)", 
 "community": "大印经典花园", 
 "detail": "未提供描述", 
 "facility": "床.衣柜.沙发.电视.冰箱.洗衣机.空调.热水器.宽带.阳台.", 
 "phone": "15120708261", 
 "rental_type": "合租 - 主卧 - 男女不限", 
 "rent": "2000", 
 "address": "\n                                银海路大印经典花园                            ", 
 "pics": [
  "http://pic1.58cdn.com.cn/anjuke_58/7df1b1575ec00225dc81fda5541182f7?w=696&h=522&crop=1", 
  "http://pic3.58cdn.com.cn/anjuke_58/3d74d101c7b025e5a30fa1e60601bb4b?w=696&h=522&crop=1", 
  "http://pic3.58cdn.com.cn/anjuke_58/8d2868d99b2aab6f47f211dee7f27d16?w=696&h=522&crop=1", 
  "http://pic3.58cdn.com.cn/anjuke_58/a1debf42fcb2f3d10c929dcb96005622?w=696&h=522&crop=1", 
  "http://pic3.58cdn.com.cn/anjuke_58/5219bd087de4459abeaf59eda8b88e80?w=696&h=522&crop=1", 
  "http://pic2.58cdn.com.cn/anjuke_58/74dfa2946a11d267c177f2bcfe0fe335?w=696&h=522&crop=1", 
  "http://pic3.58cdn.com.cn/anjuke_58/e8eb1c0ca8e5f0d563646dfba89e5149?w=696&h=522&crop=1", 
  "http://pic1.58cdn.com.cn/anjuke_58/4acecd899147219cd5c6ab48bc8a15e5?w=696&h=522&crop=1"
 ], 
 "heading": "南北  中层/共18层", 
 "lease": "面议"
}