{
 "province": "云南", 
 "city": "文山 ", 
 "advantage": [
  "新上", 
  "可短租", 
  "押一付一", 
  "南北通透", 
  "有阳台"
 ], 
 "district": "文山", 
 "title": "光大广场 1室1厅1卫(个人)", 
 "url_now": "http://ws.58.com/zufang/34508491315906x.shtml", 
 "region": "西南", 
 "area": "1室1厅1卫  20平  ", 
 "contacts": "张小姐女士(个人)", 
 "community": "文山", 
 "detail": "转租 有事要离开文山  领包入住 里面的东西我一样都不带走 生活用品什么的都有", 
 "facility": "床.衣柜.洗衣机.宽带.阳台.", 
 "phone": "站点未提供此内容", 
 "rental_type": "整租", 
 "rent": "800", 
 "address": "未提供", 
 "pics": [
  "http://pic2.58cdn.com.cn/dwater/fang/big/n_v2c2b4cfe81251443cac3de541ced53323.jpg?wt=%40%E5%BC%A0%E5%B0%8F%E5%A7%90%E5%A5%B3%E5%A3%AB&ws=f9723f6c78291aeaf9e2ce747ff2be60&w=696&h=522&crop=1", 
  "http://pic7.58cdn.com.cn/dwater/fang/big/n_v2411931ba28834119a13b9b07c2b72df2.jpg?wt=%40%E5%BC%A0%E5%B0%8F%E5%A7%90%E5%A5%B3%E5%A3%AB&ws=0d570d39298e11f0ae15a6f919692e21&w=696&h=522&crop=1", 
  "http://pic4.58cdn.com.cn/dwater/fang/big/n_v223474aa7d4bc4d50b7d0f77dd0aa0f21.jpg?wt=%40%E5%BC%A0%E5%B0%8F%E5%A7%90%E5%A5%B3%E5%A3%AB&ws=14324c15d3067bc297adb62ef0930da1&w=696&h=522&crop=1", 
  "http://pic5.58cdn.com.cn/dwater/fang/big/n_v25e4d07004a8e40b29bc8128138801d4b.jpg?wt=%40%E5%BC%A0%E5%B0%8F%E5%A7%90%E5%A5%B3%E5%A3%AB&ws=4d6c9df54b2fe5c37d53621b0dc4da11&w=696&h=522&crop=1"
 ], 
 "heading": "东  高层/共15层", 
 "lease": "押一付一"
}