{
 "province": "贵州", 
 "city": "遵义 ", 
 "advantage": [
  "配套齐全", 
  "精装修"
 ], 
 "district": "汇川", 
 "title": "人民路鹭园1楼带前后花园，精装，家电家具齐全，可办公可居家", 
 "url_now": "http://zunyi.58.com/zufang/33992532213162x.shtml", 
 "region": "西南", 
 "area": "3室1厅1卫  150平  精装修", 
 "contacts": "吴英娟(经纪人)", 
 "community": "鹭园", 
 "detail": "                      房子位于人民路鹭园，小区环境好，家电家具齐全，可以办公，可以居家，欢迎实地看房，谢谢！", 
 "facility": "床.衣柜.沙发.电视.冰箱.洗衣机.空调.热水器.宽带.阳台.", 
 "phone": "18786838631", 
 "rental_type": "整租", 
 "rent": "3500", 
 "address": "\n                                人民路                            ", 
 "pics": [
  "http://pic4.58cdn.com.cn/anjuke_58/61a33b30456db3bc394f507b5142a8c3?w=696&h=522&crop=1", 
  "http://pic6.58cdn.com.cn/anjuke_58/c8d40e3ca76f61ecd8ac87342ec24de6?w=696&h=522&crop=1", 
  "http://pic6.58cdn.com.cn/anjuke_58/ccae5c1fb3f6046b800bcfcd9c6266de?w=696&h=522&crop=1", 
  "http://pic6.58cdn.com.cn/anjuke_58/52c1f1320619bc499e21a769a20b45c2?w=696&h=522&crop=1", 
  "http://pic6.58cdn.com.cn/anjuke_58/b589fb7da5baf27cddc32471fab122b2?w=696&h=522&crop=1", 
  "http://pic6.58cdn.com.cn/anjuke_58/43c3808ccb409ddeb892729dd4802f46?w=696&h=522&crop=1", 
  "http://pic6.58cdn.com.cn/anjuke_58/43ab6a8bb4e80f5ec32a30a27f135b74?w=696&h=522&crop=1"
 ], 
 "heading": "南北  低层/共7层", 
 "lease": "年付"
}