{
 "province": "河南", 
 "city": "新乡 ", 
 "advantage": "精装修", 
 "district": "牧野", 
 "title": "出租六合园1楼 3室2厅1卫 南北通透", 
 "url_now": "http://xx.58.com/zufang/34403147082036x.shtml", 
 "region": "中南", 
 "area": "3室2厅1卫                                  138                                平  精装修 ", 
 "contacts": "郭凯(经纪人)", 
 "community": "牧野", 
 "detail": "出租六合园1楼 3室2厅1卫 南北通透 小区物业费低 有电动车棚 有车位 方便安全", 
 "facility": "床.沙发.暖气.阳台.", 
 "phone": "13462244624", 
 "rental_type": "整租", 
 "rent": "1000", 
 "address": "\n                                建北二路                            ", 
 "pics": [
  "http://pic6.58cdn.com.cn/anjuke_58/8bdb1cf05076987e5eebe04893ee96b7?w=696&h=522&crop=1"
 ], 
 "heading": "南  低层/共6层", 
 "lease": "押一付三"
}