{
 "province": "山东", 
 "city": "威海 ", 
 "advantage": [
  "配套齐全", 
  "精装修"
 ], 
 "district": "汽车站", 
 "title": "精装修，家具床沙发，入住即买新的", 
 "url_now": "http://weihai.58.com/zufang/33728510254643x.shtml", 
 "region": "华中", 
 "area": "2室2厅1卫  84平  精装修", 
 "contacts": "郑京辉(经纪人)", 
 "community": "经区", 
 "detail": "欢迎光临购房网（威海）公司：本公司在威海市内门店30余家，遍布威海经区。多年来专业的规模化经营，已储备了近3万条租售房客源，形成强大的一手房二手房买卖交易的资源体系！！！我们将用“责任、诚信、专业”的态度，门店整体联动的服务方式，快速实现您的需求！！！让您省力、省心、放心、安心！！！真心欢迎您的委托！！！", 
 "facility": "床.衣柜.沙发.电视.冰箱.洗衣机.空调.", 
 "phone": "15688711966", 
 "rental_type": "整租", 
 "rent": "2100", 
 "address": "\n                                暂无信息                            ", 
 "pics": [
  "http://pic6.58cdn.com.cn/anjuke_58/3b20ddce59b0d498ada49d164953123e?w=696&h=522&crop=1", 
  "http://pic6.58cdn.com.cn/anjuke_58/5d07082ad2d9f970258323703d3ed285?w=696&h=522&crop=1", 
  "http://pic7.58cdn.com.cn/anjuke_58/0447ea2c2e13a3f540b0ccbf6f96601a?w=696&h=522&crop=1", 
  "http://pic6.58cdn.com.cn/anjuke_58/588a68074f72014f8afda2363746d177?w=696&h=522&crop=1", 
  "http://pic1.58cdn.com.cn/anjuke_58/6e775952d54446ec040b31dd903b6b71?w=696&h=522&crop=1", 
  "http://pic1.58cdn.com.cn/anjuke_58/2c074627c680fb150b3fe471691043f2?w=696&h=522&crop=1"
 ], 
 "heading": "南北  高层/共25层", 
 "lease": "半年付押一"
}