{
 "province": "内蒙古", 
 "city": "包头 ", 
 "advantage": "配套齐全", 
 "district": "昆都仑区", 
 "title": "+紧邻银河广场+苏宁广场+万达广场+拎包入住", 
 "url_now": "http://bt.58.com/zufang/33882151823437x.shtml", 
 "region": "华北", 
 "area": "1室1厅1卫                                  50                                平  精装修 ", 
 "contacts": "崔文华(经纪人)", 
 "community": "凯旋银河线", 
 "detail": "\t", 
 "facility": "床.衣柜.沙发.电视.冰箱.洗衣机.空调.热水器.暖气.", 
 "phone": "15661559764", 
 "rental_type": "整租", 
 "rent": "1700", 
 "address": "\n                                钢铁大街,近民族东路                            ", 
 "pics": [
  "http://pic5.58cdn.com.cn/anjuke_58/79fea0b22769c9f5980fed5a80307844?w=696&h=522&crop=1", 
  "http://pic7.58cdn.com.cn/anjuke_58/c7b8eefac9a2876b45cf5032cb290105?w=696&h=522&crop=1", 
  "http://pic7.58cdn.com.cn/anjuke_58/a7329360b4a98488f5d67e2a259cd775?w=696&h=522&crop=1", 
  "http://pic6.58cdn.com.cn/anjuke_58/a3663ee16915ce32315106cd8fde57c7?w=696&h=522&crop=1", 
  "http://pic5.58cdn.com.cn/anjuke_58/c371db60fc347a7ae350877ff3ac2c07?w=696&h=522&crop=1", 
  "http://pic5.58cdn.com.cn/anjuke_58/dc1c59f8e714b082b91c7b7332607ec9?w=696&h=522&crop=1"
 ], 
 "heading": "南  中层/共27层", 
 "lease": "年付"
}