{
 "province": "湖南", 
 "city": "武汉 ", 
 "advantage": [
  "配套齐全", 
  "精装修"
 ], 
 "district": "江夏", 
 "title": "阳台大单间！直接拎包入住 湖经美院附近 阳光100精装 ！", 
 "url_now": "http://wh.58.com/zufang/34338782698034x.shtml", 
 "region": "中南", 
 "area": "1室1厅1卫  40平  精装修", 
 "contacts": "丁飞(经纪人)", 
 "community": "阳光100大湖第", 
 "detail": "未提供描述", 
 "facility": "床.衣柜.沙发.电视.冰箱.洗衣机.空调.热水器.宽带.暖气.阳台.", 
 "phone": "18827602850", 
 "rental_type": "整租", 
 "rent": "1600", 
 "address": "\n                                杨桥湖大道2号                            ", 
 "pics": [
  "http://pic5.58cdn.com.cn/anjuke_58/196513dc8162bfe5ae56b0f16c73dbae?w=696&h=522&crop=1", 
  "http://pic7.58cdn.com.cn/anjuke_58/17ca12523dfa2c508a7450a6d76ef8ea?w=696&h=522&crop=1", 
  "http://pic6.58cdn.com.cn/anjuke_58/509dd77b95d018bf9f8cb81cf8fc3212?w=696&h=522&crop=1", 
  "http://pic6.58cdn.com.cn/anjuke_58/96dc99cfadb4345df872267cbe821a22?w=696&h=522&crop=1", 
  "http://pic5.58cdn.com.cn/anjuke_58/238983633b1492330903721487850a91?w=696&h=522&crop=1"
 ], 
 "heading": "南北  中层/共27层", 
 "lease": "押一付三"
}