{
 "province": "江苏", 
 "city": "东台 ", 
 "advantage": "精装修", 
 "district": "东台市区", 
 "title": "大润发旁楼上平房二间全设施，月租1300", 
 "url_now": "http://dongtai.58.com/zufang/32923101699759x.shtml", 
 "region": "华中", 
 "area": "1室1厅1卫                                  39                                平  精装修 ", 
 "contacts": "陈永进(经纪人)", 
 "community": "东台市区", 
 "detail": "大润发附近两间平房两间，月租1300元楼上出租全设施", 
 "facility": "床.空调.", 
 "phone": "15949100287", 
 "rental_type": "整租", 
 "rent": "1300", 
 "address": "\n                                暂无信息                            ", 
 "pics": [
  "http://pic2.58cdn.com.cn/anjuke_58/095406b83c7c2db4acdf1599fedf1dec?w=696&h=522&crop=1"
 ], 
 "heading": "南  共2层", 
 "lease": "半年付"
}