{
 "province": "江苏", 
 "city": "泰兴 ", 
 "advantage": [
  "配套齐全", 
  "精装修"
 ], 
 "district": "泰兴市区", 
 "title": "凯悦大酒店附近祥生熙园1室1厅1卫，精装修，看房方便。", 
 "url_now": "http://taixing.58.com/zufang/34541029451716x.shtml", 
 "region": "华中", 
 "area": "1室1厅1卫  45平  精装修", 
 "contacts": "霍俊明(经纪人)", 
 "community": "祥生熙园", 
 "detail": "服务介绍 服务介绍公司介绍：天为易居房产经纪有限公司是经房管局备案、工商局批准成立的一家泰兴房地产市场买卖中规模较大，较正规的房产公司，专业从事二手房买卖、租赁，房地产销售代理，楼市咨询、评估的服务单位。公司于2014年4月18日姜堰成立公司秉承诚信为本，合作共赢的态度着力于为泰兴市姜堰区江阴市商品房买卖提供*及时高效的信息买卖服务，促成二手房成交，堵住二手房交易漏洞，严格把关小产权房，*，产权不清晰等.不好过户买卖的房屋信息流入市场，避免造成不必要的合同纠纷案件。易居*:为您在安家置业的路上一路保航", 
 "facility": "床.衣柜.沙发.电视.冰箱.洗衣机.空调.热水器.宽带.阳台.", 
 "phone": "13815928367", 
 "rental_type": "整租", 
 "rent": "900", 
 "address": "\n                                车站路                            ", 
 "pics": [
  "http://pic6.58cdn.com.cn/anjuke_58/2f6c0d544b434f919a7c6114a9038d08?w=696&h=522&crop=1", 
  "http://pic8.58cdn.com.cn/anjuke_58/b2d1765354971d9606d2ef8c532039ac?w=696&h=522&crop=1", 
  "http://pic2.58cdn.com.cn/anjuke_58/4cc0430002bd080c37797d8f6c65d03e?w=696&h=522&crop=1", 
  "http://pic1.58cdn.com.cn/anjuke_58/946d0d0fe66a6ae3f370be11d01b884f?w=696&h=522&crop=1", 
  "http://pic2.58cdn.com.cn/anjuke_58/5c3cfe770f44e62cba1b6641300b0f8b?w=696&h=522&crop=1"
 ], 
 "heading": "南  共1层", 
 "lease": "面议"
}