{
 "province": "广东", 
 "city": "惠州 ", 
 "advantage": [
  "配套齐全", 
  "精装修"
 ], 
 "district": "惠城", 
 "title": "公寓房 急租 实惠价 费用可打折", 
 "url_now": "http://huizhou.58.com/zufang/34413565713979x.shtml", 
 "region": "华南", 
 "area": "1室1厅1卫  58平  精装修", 
 "contacts": "简嘉仪(经纪人)", 
 "community": "佳兆业中心", 
 "detail": "未提供描述", 
 "facility": "床.衣柜.沙发.电视.冰箱.洗衣机.空调.热水器.阳台.", 
 "phone": "18688333126", 
 "rental_type": "整租", 
 "rent": "2000", 
 "address": "\n                                惠州大道9号                            ", 
 "pics": [
  "http://pic6.58cdn.com.cn/anjuke_58/ab969c7fd984bd4f0a7226c0bc979223?w=696&h=522&crop=1", 
  "http://pic5.58cdn.com.cn/anjuke_58/6af52bde9f0fc03fe09c4683a206150c?w=696&h=522&crop=1", 
  "http://pic8.58cdn.com.cn/anjuke_58/2d7f4b66f74e0a71f8a82ae5fdc10d56?w=696&h=522&crop=1", 
  "http://pic7.58cdn.com.cn/anjuke_58/551480a4d59d50e01c76ce40265e7e5a?w=696&h=522&crop=1", 
  "http://pic7.58cdn.com.cn/anjuke_58/3da57d0ec41c8b1ff1690b31286c47e1?w=696&h=522&crop=1", 
  "http://pic7.58cdn.com.cn/anjuke_58/1d921866f2a0c94f365136da88ce0f6d?w=696&h=522&crop=1"
 ], 
 "heading": "东  中层/共30层", 
 "lease": "押二付一"
}