{
 "province": "广西", 
 "city": "柳州 ", 
 "advantage": [
  "普通装修"
 ], 
 "district": "柳北", 
 "title": "家具家电全齐，公馆 2500元 2室1厅1卫 普通装修，拎包", 
 "url_now": "http://liuzhou.58.com/zufang/34491352428357x.shtml", 
 "region": "华南", 
 "area": "2室1厅1卫  78平  简单装修", 
 "contacts": "彭金德(经纪人)", 
 "community": "地王公馆", 
 "detail": "未提供描述", 
 "facility": "业主未提供此方面的信息", 
 "phone": "18077565370", 
 "rental_type": "整租", 
 "rent": "2500", 
 "address": "\n                                广场路10号                            ", 
 "pics": [
  "http://pic2.58cdn.com.cn/anjuke_58/b0f8dcc317dd46616f5e2fc7c96a0aa0?w=696&h=522&crop=1", 
  "http://pic7.58cdn.com.cn/anjuke_58/242f69c4674542d31d6f6f8e7abdeed9?w=696&h=522&crop=1", 
  "http://pic7.58cdn.com.cn/anjuke_58/e213ace1184c1a72091d995b4a3fd097?w=696&h=522&crop=1", 
  "http://pic7.58cdn.com.cn/anjuke_58/98a418907331512ba5a4c3f88140a75b?w=696&h=522&crop=1", 
  "http://pic7.58cdn.com.cn/anjuke_58/ee14dbbb7fa90c54f05b31d4140e340d?w=696&h=522&crop=1"
 ], 
 "heading": "西  中层/共53层", 
 "lease": "押一付三"
}