{
 "province": "浙江", 
 "city": "诸暨 ", 
 "advantage": [
  "精装修"
 ], 
 "district": "浣东街道", 
 "title": "江南华庭 全新精装修出租多套精装修 ，拎包入住", 
 "url_now": "http://zhuji.58.com/zufang/34198384413738x.shtml", 
 "region": "华中", 
 "area": "3室2厅2卫  110平  精装修", 
 "contacts": "陈春焕(经纪人)", 
 "community": "诸暨市区", 
 "detail": "，拎包入住 随时看房。", 
 "facility": "床.沙发.电视.冰箱.洗衣机.空调.", 
 "phone": "15258520842", 
 "rental_type": "整租", 
 "rent": "3000", 
 "address": "\n                                苎萝东路                            ", 
 "pics": [
  "http://pic2.58cdn.com.cn/anjuke_58/f4f5f530c1aab1ec279e91ab5520c23b?w=696&h=522&crop=1", 
  "http://pic6.58cdn.com.cn/anjuke_58/76107932319544c89a7bde7ea1b206b2?w=696&h=522&crop=1", 
  "http://pic6.58cdn.com.cn/anjuke_58/e28a8df336bc1fb20a09960b5264857c?w=696&h=522&crop=1", 
  "http://pic6.58cdn.com.cn/anjuke_58/10c4be8e73d7e005ab13f49fa427b82a?w=696&h=522&crop=1", 
  "http://pic5.58cdn.com.cn/anjuke_58/c08bcb2d4a89cb79d6d40d2bdd4d81b1?w=696&h=522&crop=1", 
  "http://pic5.58cdn.com.cn/anjuke_58/3b635fe0ed2ad9923f95dd1ccab397fc?w=696&h=522&crop=1"
 ], 
 "heading": "南  低层/共28层", 
 "lease": "年付"
}