{
 "province": "江西", 
 "city": "萍乡 ", 
 "advantage": [
  "配套齐全", 
  "南北通透"
 ], 
 "district": "安源", 
 "title": "汇蓝国际对面 3室1厅1卫", 
 "url_now": "http://px.58.com/zufang/22795430307872x.shtml", 
 "region": "中南", 
 "area": "3室1厅1卫  140平  ", 
 "contacts": "邬先生(经纪人)", 
 "community": "安源", 
 "detail": "\n                                                    ", 
 "facility": "床.衣柜.沙发.电视.冰箱.洗衣机.空调.热水器.宽带.", 
 "phone": "13635948788", 
 "rental_type": "整租", 
 "rent": "1500", 
 "address": "\n                                暂无信息                            ", 
 "pics": [
  "http://pic3.58cdn.com.cn/p1/big/n_v1bkujjdyeqc3vl2md5rwa.jpg?w=696&h=522&crop=1", 
  "http://pic4.58cdn.com.cn/p1/big/n_v1bl2lwtiiqc3vlu2eluda.jpg?w=696&h=522&crop=1", 
  "http://pic5.58cdn.com.cn/p1/big/n_v1bkuyfvimqc3vltqxouea.jpg?w=696&h=522&crop=1", 
  "http://pic8.58cdn.com.cn/p1/big/n_v1bkuymcyoqc3vldys2mhq.jpg?w=696&h=522&crop=1", 
  "http://pic7.58cdn.com.cn/p1/big/n_v1bl2lwwitqc3vlcw27byq.jpg?w=696&h=522&crop=1", 
  "http://pic2.58cdn.com.cn/p1/big/n_v1bl2lwwixqc3vkf7uzigq.jpg?w=696&h=522&crop=1"
 ], 
 "heading": "南北  中层/共7层", 
 "lease": "押一付三"
}