{
 "province": "安徽", 
 "city": "淮南 ", 
 "advantage": [
  "精装修"
 ], 
 "district": "田家庵", 
 "title": "阳光国际城两室两厅精装修拎包入住", 
 "url_now": "http://hn.58.com/zufang/33650196579791x.shtml", 
 "region": "华中", 
 "area": "2室2厅1卫                                  90                                平  精装修 ", 
 "contacts": "侯纪峰(经纪人)", 
 "community": "阳光国际城", 
 "detail": "洞山东路，交通便利环境好，矿一中*房，家具家电齐全精装修拎", 
 "facility": "业主未提供此方面的信息", 
 "phone": "15755406266", 
 "rental_type": "整租", 
 "rent": "1600", 
 "address": "\n                                暂无信息                            ", 
 "pics": [
  "http://pic6.58cdn.com.cn/anjuke_58/f2425776910646f3c8cd31898d190024?w=696&h=522&crop=1", 
  "http://pic8.58cdn.com.cn/anjuke_58/d13de05966a36229aa0c73be818fed51?w=696&h=522&crop=1", 
  "http://pic8.58cdn.com.cn/anjuke_58/644c4f343656e95587faad469510e9fe?w=696&h=522&crop=1", 
  "http://pic8.58cdn.com.cn/anjuke_58/3b24784f941a37cd7f61a038deb161b6?w=696&h=522&crop=1", 
  "http://pic7.58cdn.com.cn/anjuke_58/97546d26c9d2327cd84469d4353c2863?w=696&h=522&crop=1", 
  "http://pic8.58cdn.com.cn/anjuke_58/0acb11c7d1194bef5fe3f2381e34b160?w=696&h=522&crop=1", 
  "http://pic2.58cdn.com.cn/anjuke_58/657457a1f987f4b73b3e39a156ba97c4?w=696&h=522&crop=1", 
  "http://pic2.58cdn.com.cn/anjuke_58/748bfa6e2086593c35c10535ffe965f0?w=696&h=522&crop=1", 
  "http://pic2.58cdn.com.cn/anjuke_58/56deaad9fff7ee7326d6eea50d1308db?w=696&h=522&crop=1"
 ], 
 "heading": "南北  低层/共18层", 
 "lease": "押一付三"
}