{
 "province": "浙江", 
 "city": "诸暨 ", 
 "advantage": [
  "配套齐全", 
  "精装修"
 ], 
 "district": "浣东街道", 
 "title": "万达广场附近，翡翠园，精装修，装修清爽，拎包入住，欢迎看房", 
 "url_now": "http://zhuji.58.com/zufang/34506685785018x.shtml", 
 "region": "华中", 
 "area": "3室2厅1卫  90平  精装修", 
 "contacts": "陈卫卫(经纪人)", 
 "community": "诸暨市区", 
 "detail": "万达广场旁，翡翠园精装修，装修清爽，拎包入住，欢迎看房", 
 "facility": "床.衣柜.沙发.电视.冰箱.洗衣机.空调.热水器.阳台.", 
 "phone": "18069614202", 
 "rental_type": "整租", 
 "rent": "2700", 
 "address": "\n                                高湖路                            ", 
 "pics": [
  "http://pic2.58cdn.com.cn/anjuke_58/882969044d1491f5f04f11cc26dedfcc?w=696&h=522&crop=1"
 ], 
 "heading": "南  低层/共15层", 
 "lease": "年付"
}