{
 "province": "山东", 
 "city": "泰安 ", 
 "advantage": [
  "精装修"
 ], 
 "district": "泰山区", 
 "title": "岱宗大街齐鲁对过 邮电局宿舍 3室 精装修 拎包入住", 
 "url_now": "http://ta.58.com/zufang/34502705430079x.shtml", 
 "region": "华中", 
 "area": "3室1厅1卫  80平  精装修", 
 "contacts": "刘国栋(经纪人)", 
 "community": "邮电局二宿舍", 
 "detail": "拎包入住........13335294868", 
 "facility": "空调.热水器.阳台.", 
 "phone": "13335294868", 
 "rental_type": "整租", 
 "rent": "1500", 
 "address": "\n                                奈河西路13号                            ", 
 "pics": [
  "http://pic6.58cdn.com.cn/anjuke_58/2b512282fa642b0dc0365543d512ebbe?w=696&h=522&crop=1", 
  "http://pic4.58cdn.com.cn/anjuke_58/49e3277596322d6daaac36aa750d6235?w=696&h=522&crop=1", 
  "http://pic3.58cdn.com.cn/anjuke_58/7649fb3d73c008a5502a1a613bd836ad?w=696&h=522&crop=1", 
  "http://pic4.58cdn.com.cn/anjuke_58/9c5fd424ec64a350c342bd5c23ac3067?w=696&h=522&crop=1", 
  "http://pic6.58cdn.com.cn/anjuke_58/ea45b94947beadeecd4b7998ed85e676?w=696&h=522&crop=1"
 ], 
 "heading": "南北  共4层", 
 "lease": "面议"
}