{
 "province": "山东", 
 "city": "威海 ", 
 "advantage": "精装修", 
 "district": "经区", 
 "title": "芙蓉花园两室两厅南北通透精装修家电齐全年租2000", 
 "url_now": "http://weihai.58.com/zufang/34459899864384x.shtml", 
 "region": "华中", 
 "area": "2室2厅1卫                                  95                                平  精装修 ", 
 "contacts": "刘珊(经纪人)", 
 "community": "芙蓉花园", 
 "detail": "未提供描述", 
 "facility": "业主未提供此方面的信息", 
 "phone": "15266156559", 
 "rental_type": "整租", 
 "rent": "2000", 
 "address": "\n                                上海路7号                            ", 
 "pics": [
  "http://pic1.58cdn.com.cn/anjuke_58/e48cb5fbb31af999d385bcce5a476b36?w=696&h=522&crop=1", 
  "http://pic3.58cdn.com.cn/anjuke_58/1e61eeb6fbc911f434a2614ada272b1e?w=696&h=522&crop=1", 
  "http://pic3.58cdn.com.cn/anjuke_58/bc00aa8746e4675e1db2013da1b309b1?w=696&h=522&crop=1", 
  "http://pic3.58cdn.com.cn/anjuke_58/d6ad177b4f908abb51453a1a79243365?w=696&h=522&crop=1", 
  "http://pic2.58cdn.com.cn/anjuke_58/b57d2a2304d33df8b43cf8ca6a4ce324?w=696&h=522&crop=1", 
  "http://pic1.58cdn.com.cn/anjuke_58/96c27731f065af3004400016d73d9a5c?w=696&h=522&crop=1", 
  "http://pic1.58cdn.com.cn/anjuke_58/2b20da14ed9ed8935e7e398970adc88b?w=696&h=522&crop=1"
 ], 
 "heading": "南北  中层/共6层", 
 "lease": "押一付三"
}