{
 "province": "浙江", 
 "city": "丽水 ", 
 "advantage": [
  "配套齐全", 
  "精装修"
 ], 
 "district": "其他", 
 "title": "九和单身公寓.1室1厅1卫1厨房1阳台小区房标准租金1600", 
 "url_now": "http://short.58.com/zd_p/01ca8ad7-391f-4062-8455-a927930321b7/?target=njfevj-16-xgk_hvimob_85147591635962q-feykn&end=end", 
 "region": "华中", 
 "area": "1室1厅1卫  55平  精装修", 
 "contacts": "丁继欢(经纪人)", 
 "community": "莲都", 
 "detail": "未提供描述", 
 "facility": "床.衣柜.沙发.电视.冰箱.洗衣机.空调.热水器.宽带.暖气.阳台.", 
 "phone": "15988051223", 
 "rental_type": "整租", 
 "rent": "1600", 
 "address": "\n                                暂无信息                            ", 
 "pics": [
  "http://pic1.58cdn.com.cn/anjuke_58/08ec8074c908989d7731a3970f21cd9c?w=696&h=522&crop=1", 
  "http://pic8.58cdn.com.cn/anjuke_58/e8a38d1dd68041e6465a254a099acaad?w=696&h=522&crop=1", 
  "http://pic7.58cdn.com.cn/anjuke_58/746af0e22ac62ecb81b57b1f8a70f471?w=696&h=522&crop=1", 
  "http://pic7.58cdn.com.cn/anjuke_58/20f4d67d52696a6b2a730d1833934ee5?w=696&h=522&crop=1", 
  "http://pic7.58cdn.com.cn/anjuke_58/82f24fa99ea2e719ee645f1177782141?w=696&h=522&crop=1"
 ], 
 "heading": "南  中层/共6层", 
 "lease": "押一付三"
}