{
 "province": "湖南", 
 "city": "武汉 ", 
 "advantage": [
  "邻地铁", 
  "配套齐全", 
  "精装修"
 ], 
 "district": "武昌", 
 "title": "仁和路双地铁口，金地自在城精装一房，价格实惠，交通便利！！！", 
 "url_now": "http://wh.58.com/zufang/34501595420969x.shtml", 
 "region": "中南", 
 "area": "1室0厅0卫  37平  精装修", 
 "contacts": "林方卓(经纪人)", 
 "community": "金地自在城(东区)", 
 "detail": "周边配套完善，小区管理完善，内设有儿童游玩区,环境优美，空气清房源特色户型方正，采光通风好。超市，多家银行。多条公交经过。", 
 "facility": "床.衣柜.沙发.电视.冰箱.洗衣机.热水器.", 
 "phone": "15827407556", 
 "rental_type": "整租", 
 "rent": "1000", 
 "address": "\n                                团结大道                            ", 
 "pics": [
  "http://pic6.58cdn.com.cn/anjuke_58/c3d43a509cc109682413a518a61ceece?w=696&h=522&crop=1", 
  "http://pic7.58cdn.com.cn/anjuke_58/b31db5a3aa58a21f2e38e84af086a4c3?w=696&h=522&crop=1"
 ], 
 "heading": "南  低层/共34层", 
 "lease": "押一付三"
}