{
 "province": "新疆", 
 "city": "喀什 ", 
 "advantage": [
  "普通装修"
 ], 
 "district": "喀什", 
 "title": "阳光小区，大户型，采光好，简单装修，急于出租。", 
 "url_now": "http://ks.58.com/zufang/34491016209194x.shtml", 
 "region": "西北", 
 "area": "3室1厅1卫  105平  简单装修", 
 "contacts": "朱永鹏(经纪人)", 
 "community": "公务员阳光小区高层", 
 "detail": "未提供描述", 
 "facility": "热水器.宽带.暖气.阳台.", 
 "phone": "13999094849", 
 "rental_type": "整租", 
 "rent": "1350", 
 "address": "\n                                远方市场附近                            ", 
 "pics": [
  "http://pic1.58cdn.com.cn/anjuke_58/9c4388ef3de2bd576e446869b567e25b?w=696&h=522&crop=1", 
  "http://pic1.58cdn.com.cn/anjuke_58/f9ea0971161bed5f80109cdcfa8e3c1c?w=696&h=522&crop=1", 
  "http://pic3.58cdn.com.cn/anjuke_58/fc7980b4668ae23a23c21b399a0f774a?w=696&h=522&crop=1", 
  "http://pic3.58cdn.com.cn/anjuke_58/78e65e39ff5fe4938ca909ab8c6752b2?w=696&h=522&crop=1", 
  "http://pic3.58cdn.com.cn/anjuke_58/f4a3a5c1fc6a4b11b48fca86674180da?w=696&h=522&crop=1", 
  "http://pic3.58cdn.com.cn/anjuke_58/8d76829032b2aecc8a8cbabb2523ee53?w=696&h=522&crop=1", 
  "http://pic2.58cdn.com.cn/anjuke_58/da4827e4e79b609fa2b0f0696d783413?w=696&h=522&crop=1"
 ], 
 "heading": "东南  高层/共17层", 
 "lease": "年付"
}