{
 "province": "湖南", 
 "city": "孝感 ", 
 "advantage": [
  "普通装修"
 ], 
 "district": "孝南", 
 "title": "百佳豪庭 3室2厅 诚心出租", 
 "url_now": "http://xiaogan.58.com/zufang/34316565512630x.shtml", 
 "region": "中南", 
 "area": "3室2厅1卫  120平  简单装修", 
 "contacts": "王淑芬(经纪人)", 
 "community": "百佳豪庭", 
 "detail": "未提供描述", 
 "facility": "业主未提供此方面的信息", 
 "phone": "15826850892", 
 "rental_type": "整租", 
 "rent": "1500", 
 "address": "\n                                城站路                            ", 
 "pics": [
  "http://pic4.58cdn.com.cn/anjuke_58/96f9d06a7403aefc34de2415e6418734?w=696&h=522&crop=1", 
  "http://pic6.58cdn.com.cn/anjuke_58/385cdb78a0312215764c63bc126031ca?w=696&h=522&crop=1", 
  "http://pic6.58cdn.com.cn/anjuke_58/966816a63c306ffa1c83664797798c5f?w=696&h=522&crop=1", 
  "http://pic6.58cdn.com.cn/anjuke_58/540947ab290f3c03890548904afde150?w=696&h=522&crop=1", 
  "http://pic5.58cdn.com.cn/anjuke_58/ea1b93fa288ae7a4adc621ec704ebe07?w=696&h=522&crop=1", 
  "http://pic5.58cdn.com.cn/anjuke_58/0c25afe6699714bf7abf62db86ab2bff?w=696&h=522&crop=1", 
  "http://pic5.58cdn.com.cn/anjuke_58/bbe88891c769a15301dc4877258bc63a?w=696&h=522&crop=1", 
  "http://pic4.58cdn.com.cn/anjuke_58/e2b5afad2e4361de18bc59df062dc795?w=696&h=522&crop=1", 
  "http://pic4.58cdn.com.cn/anjuke_58/3d626bff2c7f26d93c95b7ccd761c7a1?w=696&h=522&crop=1"
 ], 
 "heading": "南  中层/共7层", 
 "lease": "年付"
}