{
 "province": "安徽", 
 "city": "铜陵 ", 
 "advantage": [
  "配套齐全", 
  "精装修"
 ], 
 "district": "铜官山", 
 "title": "飞越大都汇 2室1厅1卫 精装修 家电家具齐全", 
 "url_now": "http://tongling.58.com/zufang/34504439748653x.shtml", 
 "region": "华中", 
 "area": "2室1厅1卫  90平  精装修", 
 "contacts": "周伟(经纪人)", 
 "community": "飞越大都汇(学士路)", 
 "detail": "飞越大都汇 2室1厅1卫 精装修 家电家具齐全", 
 "facility": "床.衣柜.沙发.电视.冰箱.洗衣机.空调.热水器.", 
 "phone": "13956243152", 
 "rental_type": "整租", 
 "rent": "1300", 
 "address": "\n                                学士路,近谢珑路                            ", 
 "pics": [
  "http://pic4.58cdn.com.cn/anjuke_58/bb18a1960afa29a9e28e6658de261396?w=696&h=522&crop=1", 
  "http://pic2.58cdn.com.cn/anjuke_58/795f7cde0509e1d42ee65ed4a4496f86?w=696&h=522&crop=1"
 ], 
 "heading": "南  低层/共9层", 
 "lease": "面议"
}