{
 "province": "四川", 
 "city": "泸州 ", 
 "advantage": [
  "独立阳台", 
  "普通装修"
 ], 
 "district": "江阳", 
 "title": "(单间出租)无介绍费 市中心 东门口附近 港华苑 次卧出租", 
 "url_now": "http://luzhou.58.com/hezu/34479851312446x.shtml", 
 "region": "西南", 
 "area": "4室2厅2卫  15平  简单装修", 
 "contacts": "谢津生(经纪人)", 
 "community": "港华苑", 
 "detail": "未提供描述", 
 "facility": "床.洗衣机.空调.热水器.宽带.", 
 "phone": "15196053310", 
 "rental_type": "合租 - 次卧 - 男女不限", 
 "rent": "400", 
 "address": "\n                                东门口附近                            ", 
 "pics": [
  "http://pic8.58cdn.com.cn/anjuke_58/60cdc3fe1c1942e64858506a71a69121?w=696&h=522&crop=1", 
  "http://pic8.58cdn.com.cn/anjuke_58/ed59ccd860cb3fca8d62277c3f480a84?w=696&h=522&crop=1", 
  "http://pic8.58cdn.com.cn/anjuke_58/7febea791145380f5ee340ca613fc551?w=696&h=522&crop=1"
 ], 
 "heading": "东北  高层/共9层", 
 "lease": "押二付三"
}