{
 "province": "湖南", 
 "city": "武汉 ", 
 "advantage": "配套齐全", 
 "district": "未填写", 
 "title": "金桥汇2期（公寓） 1室1厅1卫(个人)", 
 "url_now": "http://wh.58.com/zufang/30302297165378x.shtml", 
 "region": "中南", 
 "area": "1室1厅1卫                                  63                                平  精装修 ", 
 "contacts": "张先生(个人)", 
 "community": "金桥汇2期（公寓）", 
 "detail": "未提供描述", 
 "facility": "床.衣柜.沙发.冰箱.洗衣机.空调.热水器.阳台.", 
 "phone": "站点未提供此内容", 
 "rental_type": "整租", 
 "rent": "1850", 
 "address": "\n                                暂无信息                            ", 
 "pics": [
  "http://pic8.58cdn.com.cn/p1/big/n_v1bkujjdzdmm3ftiy6gi6a.jpg?w=696&h=522&crop=1", 
  "http://pic5.58cdn.com.cn/p1/big/n_v1bkuymczrmm3ftvabinha.jpg?w=696&h=522&crop=1", 
  "http://pic1.58cdn.com.cn/p1/big/n_v1bkuyfvj3mm3fttgmo5kq.jpg?w=696&h=522&crop=1", 
  "http://pic1.58cdn.com.cn/p1/big/n_v1bl2lwwkdmm3ftnck7qzq.jpg?w=696&h=522&crop=1", 
  "http://pic1.58cdn.com.cn/p1/big/n_v1bl2lwwkmmm3fs2g3qufa.jpg?w=696&h=522&crop=1", 
  "http://pic3.58cdn.com.cn/p1/big/n_v1bl2lwxstmm3fsiu4ayfq.jpg?w=696&h=522&crop=1", 
  "http://pic1.58cdn.com.cn/p1/big/n_v1bkuymc24mm3fs35wuqtq.jpg?w=696&h=522&crop=1"
 ], 
 "heading": "南北  高层/共31层", 
 "lease": "押一付三"
}