{
 "province": "湖南", 
 "city": "宜昌 ", 
 "advantage": "配套齐全", 
 "district": "伍家岗", 
 "title": "五一广场附近 东郡B区 缺少家电可配齐 拎包即住", 
 "url_now": "http://yc.58.com/zufang/34394836849215x.shtml", 
 "region": "中南", 
 "area": "2室2厅1卫                                  85                                平  精装修 ", 
 "contacts": "李鹏(经纪人)", 
 "community": "弘洋东郡B区", 
 "detail": "五一广场附近 东郡B区 缺少家电可配齐 拎包即住", 
 "facility": "床.衣柜.沙发.电视.冰箱.洗衣机.空调.热水器.阳台.", 
 "phone": "13477111148", 
 "rental_type": "整租", 
 "rent": "2200", 
 "address": "\n                                伍临路                            ", 
 "pics": [
  "http://pic1.58cdn.com.cn/anjuke_58/80bb970231ee864b4a326c659876700a?w=696&h=522&crop=1", 
  "http://pic2.58cdn.com.cn/anjuke_58/237db8bc35b19d40e79b80fdb8202618?w=696&h=522&crop=1", 
  "http://pic5.58cdn.com.cn/anjuke_58/9c00f04305a7e6f533dcc22c911d7a24?w=696&h=522&crop=1", 
  "http://pic5.58cdn.com.cn/anjuke_58/abe9128d5d32dc92c8e087a83ed1d79a?w=696&h=522&crop=1", 
  "http://pic4.58cdn.com.cn/anjuke_58/0530f2f0c32fcbe3f800d9ecc7fa3594?w=696&h=522&crop=1", 
  "http://pic5.58cdn.com.cn/anjuke_58/a20e993e1bf90dfebefd24c3001fdc94?w=696&h=522&crop=1"
 ], 
 "heading": "南  中层/共28层", 
 "lease": "押一付三"
}