{
 "province": "青海", 
 "city": "西宁 ", 
 "advantage": [
  "普通装修"
 ], 
 "district": "城西", 
 "title": "繁华地段 交通便利 办公好房", 
 "url_now": "http://xn.58.com/zufang/34173675013042x.shtml", 
 "region": "西北", 
 "area": "2室2厅1卫                                  104                                平  简单装修 ", 
 "contacts": "姚艳芳(经纪人)", 
 "community": "力盟尚都", 
 "detail": "未提供描述", 
 "facility": "热水器.宽带.暖气.", 
 "phone": "13109707017", 
 "rental_type": "整租", 
 "rent": "3200", 
 "address": "未提供", 
 "pics": [
  "http://pic3.58cdn.com.cn/anjuke_58/87bc4eafa4a47d8b8ca452b4a73672e5?w=696&h=522&crop=1", 
  "http://pic6.58cdn.com.cn/anjuke_58/2514d3102850069d9491c41c5c6714ce?w=696&h=522&crop=1", 
  "http://pic5.58cdn.com.cn/anjuke_58/121cb945d5df6557d6f32e98418fecd3?w=696&h=522&crop=1", 
  "http://pic5.58cdn.com.cn/anjuke_58/c07ec3371efef1d83d848580edff0c72?w=696&h=522&crop=1", 
  "http://pic5.58cdn.com.cn/anjuke_58/04febd133e45a1075a3f543200c45a6f?w=696&h=522&crop=1", 
  "http://pic5.58cdn.com.cn/anjuke_58/12962a2f28043b18dc043cf13a4220e0?w=696&h=522&crop=1", 
  "http://pic5.58cdn.com.cn/anjuke_58/b80b1fcb1c3219c51647f46c71c1c943?w=696&h=522&crop=1", 
  "http://pic5.58cdn.com.cn/anjuke_58/3716927c33636b7a33263404476f4f4f?w=696&h=522&crop=1", 
  "http://pic3.58cdn.com.cn/anjuke_58/ac07c4c94e6739880972ba771ebc9261?w=696&h=522&crop=1"
 ], 
 "heading": "南  高层/共33层", 
 "lease": "年付"
}