{
 "province": "安徽", 
 "city": "马鞍山 ", 
 "advantage": [
  "配套齐全", 
  "精装修"
 ], 
 "district": "花山", 
 "title": "碧云天城市花园精装大三室，拎包入住", 
 "url_now": "http://mas.58.com/zufang/33199999396688x.shtml", 
 "region": "华中", 
 "area": "3室2厅2卫  135平  精装修", 
 "contacts": "储计划(经纪人)", 
 "community": "碧云天城市花园", 
 "detail": "碧云天城市花园南北通透，家电家具齐全，拎包入住", 
 "facility": "床.衣柜.沙发.电视.冰箱.洗衣机.空调.热水器.阳台.", 
 "phone": "15105554282", 
 "rental_type": "整租", 
 "rent": "2600", 
 "address": "\n                                花山雨山路湖东中路                            ", 
 "pics": [
  "http://pic6.58cdn.com.cn/anjuke_58/6a66a7ef46ec30d70fe5569bf03e03ab?w=696&h=522&crop=1"
 ], 
 "heading": "南北  中层/共6层", 
 "lease": "押一付三"
}