{
 "province": "山东", 
 "city": "泰安 ", 
 "advantage": [
  "配套齐全", 
  "普通装修"
 ], 
 "district": "岱岳区", 
 "title": "万达广场 御驾新苑 精装修家具家电齐全拎包入住 长城中学", 
 "url_now": "http://ta.58.com/zufang/34203389255348x.shtml", 
 "region": "华中", 
 "area": "2室2厅1卫  107平  简单装修", 
 "contacts": "齐花英(经纪人)", 
 "community": "御驾新苑A区", 
 "detail": "未提供描述", 
 "facility": "床.衣柜.沙发.冰箱.洗衣机.热水器.暖气.阳台.", 
 "phone": "13455481332", 
 "rental_type": "整租", 
 "rent": "1500", 
 "address": "\n                                长城路                            ", 
 "pics": [
  "http://pic2.58cdn.com.cn/anjuke_58/0e1ce110b1281516c1727742fbe725c0?w=696&h=522&crop=1", 
  "http://pic4.58cdn.com.cn/anjuke_58/634080818a7322187829f9dcf8e1d191?w=696&h=522&crop=1", 
  "http://pic6.58cdn.com.cn/anjuke_58/d09bb20dcabde179c1e9481615c07c54?w=696&h=522&crop=1", 
  "http://pic6.58cdn.com.cn/anjuke_58/a2c33f63ea37df4b4c3abd21011df15c?w=696&h=522&crop=1"
 ], 
 "heading": "南北  中层/共28层", 
 "lease": "面议"
}