{
 "province": "江西", 
 "city": "萍乡 ", 
 "advantage": [
  "押一付一", 
  "配套齐全", 
  "南北通透", 
  "有阳台", 
  "随时看房"
 ], 
 "district": "安源", 
 "title": "新世纪对面供电局家属小区 2室2厅1卫 80平方 750元 2室2厅1卫(个人)", 
 "url_now": "http://px.58.com/zufang/34507210545195x.shtml", 
 "region": "中南", 
 "area": "2室2厅1卫  80平  中等装修", 
 "contacts": "唐女士(个人)", 
 "community": "安源", 
 "detail": "\n                                                    ", 
 "facility": "床.衣柜.沙发.电视.冰箱.洗衣机.空调.热水器.宽带.阳台.", 
 "phone": "站点未提供此内容", 
 "rental_type": "整租", 
 "rent": "750", 
 "address": "未提供", 
 "pics": [], 
 "heading": "南北  低层/共7层", 
 "lease": "押一付一"
}