{
 "province": "安徽", 
 "city": "滁州 ", 
 "advantage": [
  "配套齐全", 
  "普通装修"
 ], 
 "district": "南谯", 
 "title": "天逸华府桂园简单装修包物业", 
 "url_now": "http://chuzhou.58.com/zufang/34483422315075x.shtml", 
 "region": "华中", 
 "area": "3室2厅1卫  123平  简单装修", 
 "contacts": "侯永(经纪人)", 
 "community": "天逸华府桂园", 
 "detail": "天逸华府桂园简单装修包物业   天逸华府桂园简单装修包物业", 
 "facility": "床.衣柜.冰箱.洗衣机.空调.热水器.阳台.", 
 "phone": "17755079016", 
 "rental_type": "整租", 
 "rent": "1000", 
 "address": "\n                                龙蟠大道                            ", 
 "pics": [
  "http://pic8.58cdn.com.cn/anjuke_58/c233c26f8a96966aefaa4a5b95e48c2f?w=696&h=522&crop=1", 
  "http://pic8.58cdn.com.cn/anjuke_58/7ff6fbdefb7805a7258f2fef3781e36a?w=696&h=522&crop=1", 
  "http://pic7.58cdn.com.cn/anjuke_58/89ea5817ab73a21a3bf058129ae29779?w=696&h=522&crop=1", 
  "http://pic2.58cdn.com.cn/anjuke_58/c926c963a21ea72ed2e6d7ebd798bcd5?w=696&h=522&crop=1"
 ], 
 "heading": "南北  中层/共18层", 
 "lease": "押一付三"
}