{
 "province": "浙江", 
 "city": "诸暨 ", 
 "advantage": "配套齐全", 
 "district": "暨阳街道", 
 "title": "翡翠苑欧式精装修 多套出租，欢迎看房子", 
 "url_now": "http://zhuji.58.com/zufang/31384049715265x.shtml", 
 "region": "华中", 
 "area": "2室2厅1卫                                  98                                平  精装修 ", 
 "contacts": "徐雪颖(经纪人)", 
 "community": "诸暨市区", 
 "detail": "空2，热水器，电视机，洗衣机，冰箱，组合家具，地砖，设施齐全", 
 "facility": "床.衣柜.沙发.电视.冰箱.洗衣机.空调.热水器.宽带.暖气.阳台.", 
 "phone": "13606564905", 
 "rental_type": "整租", 
 "rent": "3600", 
 "address": "\n                                暂无信息                            ", 
 "pics": [
  "http://pic1.58cdn.com.cn/anjuke_58/02eb4aacc519ca1d97fefde93acfaad6?w=696&h=522&crop=1", 
  "http://pic8.58cdn.com.cn/anjuke_58/076ec7e0f132e08568e904047124915c?w=696&h=522&crop=1", 
  "http://pic2.58cdn.com.cn/anjuke_58/be352872e1e87cdde3f6499a882af6e5?w=696&h=522&crop=1", 
  "http://pic3.58cdn.com.cn/anjuke_58/210ebfff46df11d36ac66783702f2fe0?w=696&h=522&crop=1", 
  "http://pic2.58cdn.com.cn/anjuke_58/49356bb121f8af70adbf7f1c794263bb?w=696&h=522&crop=1", 
  "http://pic2.58cdn.com.cn/anjuke_58/ed5bc0baabf7c27868345c27d9494cd9?w=696&h=522&crop=1", 
  "http://pic2.58cdn.com.cn/anjuke_58/1da3d471c7b1ab6419a1d3e47d6c6474?w=696&h=522&crop=1", 
  "http://pic2.58cdn.com.cn/anjuke_58/708ff82883a736c9f31be09802f4c0c6?w=696&h=522&crop=1"
 ], 
 "heading": "南  低层/共18层", 
 "lease": "年付"
}